Metadata-Version: 1.1
Name: som-pbc
Version: 1.0.1
Summary: self organizing maps with periodic boundary conditions
Home-page: https://github.com/alexarnimueller/som
Author: Alex Müller
Author-email: alexarnimueller@protonmail.com
License: MIT
Keywords: SOM embedding machine learning chemoinformatics bioinformatics datascience descriptor similarity
Platform: UNKNOWN
Classifier: Development Status :: 5 - Production/Stable
Classifier: Intended Audience :: Science/Research
Classifier: Topic :: Scientific/Engineering :: Bio-Informatics
Classifier: Topic :: Scientific/Engineering :: Chemistry
Classifier: Topic :: Scientific/Engineering :: Medical Science Apps.
Classifier: License :: OSI Approved :: MIT License
Classifier: Programming Language :: Python :: 3
Classifier: Programming Language :: Python :: 3.6
